{
    "version": "2.3.0",
    "description": "FAgram Desktop is a custom Telegram client.",
    "homepage": "https://github.com/fagramdesktop/fadesktop",
    "license": {
        "identifier": "GPL-3.0-openssl-exception",
        "url": "https://github.com/fagramdesktop/fadesktop/blob/dev/LICENSE"
    },
    "architecture": {
        "64bit": {
            "url": "https://github.com/fagramdesktop/fadesktop/releases/download/2.3.0/FAgram_Win-x64_2.3.0_portable.zip",
            "hash": "69097c306097ada6a46a1be2e129c1b2ceb1675f1642a49c67e7016f6680964b"
        }
    },
    "shortcuts": [
        [
            "fagram.exe",
            "FAgram",
            "",
            "icon.ico"
        ]
    ],
    "persist": "tdata"
}
